m3utool/__init__.py
m3utool/async_request.py
m3utool/config.py
m3utool/download.py
m3utool/encryption.py
m3utool/httpclient.py
m3utool/m3u8parse.py
m3utool/model.py
m3utool-0.0.2.dist-info/LICENSE
m3utool-0.0.2.dist-info/METADATA
m3utool-0.0.2.dist-info/WHEEL
m3utool-0.0.2.dist-info/top_level.txt
m3utool-0.0.2.dist-info/RECORD
