Metadata-Version: 2.1
Name: m3utool
Version: 0.0.2
Summary: m3u8 downloader
Home-page: 
Author: PengKe
Author-email: 925330867@qq.com
Classifier: Programming Language :: Python :: 3
Classifier: License :: OSI Approved :: MIT License
Classifier: Operating System :: OS Independent
Requires-Python: >=3.8
License-File: LICENSE
Requires-Dist: xctools
Requires-Dist: pycryptodome
Requires-Dist: m3u8
Requires-Dist: requests
Requires-Dist: aiofiles
Requires-Dist: aiohttp
